AUTHORS
ChangeLog
LICENSE
README.rst
requirements.txt
setup.cfg
setup.py
bin/robotice-cc2541
cc2541/__init__.py
cc2541/cc2541.py
cc2541/driver.py
cc2541/sensor.py
cc2541/utils.py
robotice_cc2541_device.egg-info/PKG-INFO
robotice_cc2541_device.egg-info/SOURCES.txt
robotice_cc2541_device.egg-info/dependency_links.txt
robotice_cc2541_device.egg-info/entry_points.txt
robotice_cc2541_device.egg-info/not-zip-safe
robotice_cc2541_device.egg-info/requires.txt
robotice_cc2541_device.egg-info/top_level.txt